tfmake/Makefile.aws
tfmake/Makefile.azure
tfmake/__init__.py
tfmake/cli.py
tfmake/custom/__init__.py
tfmake/templates/tfmake.aws.j2
tfmake/templates/tfmake.azure.j2
tfmake-1.0.61.dist-info/WHEEL
tfmake-1.0.61.dist-info/entry_points.txt
tfmake-1.0.61.dist-info/METADATA
tfmake-1.0.61.dist-info/RECORD
