Metadata-Version: 2.1
Name: tfmake
Version: 1.0.61
Summary: Python based Makefile wrapper for terraform projects
Home-page: https://gitlab.com/lunadata/tfmake
Author: LunaData
Author-email: lunadata@4synergy.nl
Requires-Python: >=3.6,<4.0
Classifier: Programming Language :: Python :: 3
Classifier: Programming Language :: Python :: 3.6
Classifier: Programming Language :: Python :: 3.7
Classifier: Programming Language :: Python :: 3.8
Classifier: Programming Language :: Python :: 3.9
Classifier: Programming Language :: Python :: 3.10
Classifier: Programming Language :: Python :: 3.11
Requires-Dist: Jinja2 (>=3,<4)
Requires-Dist: PyYAML (>=5.3.1)
Requires-Dist: click (>=7.0)
Requires-Dist: outdated (>=0.2.0)
Requires-Dist: pathlib (>=1.0.1,<2.0.0)
Project-URL: Repository, https://gitlab.com/lunadata/tfmake
